{
  "id": "2308433",
  "name": "music",
  "font_family": "iconfont",
  "css_prefix_text": "icon-",
  "description": "",
  "glyphs": [
    {
      "icon_id": "300727",
      "name": "三角右",
      "font_class": "triangle-right",
      "unicode": "e62c",
      "unicode_decimal": 58924
    },
    {
      "icon_id": "300757",
      "name": "三角左",
      "font_class": "triangle-left",
      "unicode": "e62d",
      "unicode_decimal": 58925
    },
    {
      "icon_id": "996523",
      "name": "暂停",
      "font_class": "ai07",
      "unicode": "e67b",
      "unicode_decimal": 59003
    },
    {
      "icon_id": "1447738",
      "name": "播放",
      "font_class": "bofang2",
      "unicode": "e618",
      "unicode_decimal": 58904
    },
    {
      "icon_id": "11177667",
      "name": "循环",
      "font_class": "ziyuan",
      "unicode": "e619",
      "unicode_decimal": 58905
    },
    {
      "icon_id": "36566",
      "name": "播放",
      "font_class": "bofang",
      "unicode": "e600",
      "unicode_decimal": 58880
    },
    {
      "icon_id": "55147",
      "name": "下载",
      "font_class": "46",
      "unicode": "e639",
      "unicode_decimal": 58937
    },
    {
      "icon_id": "827650",
      "name": "评论",
      "font_class": "pinglun",
      "unicode": "e664",
      "unicode_decimal": 58980
    },
    {
      "icon_id": "1554904",
      "name": "更多",
      "font_class": "gengduo",
      "unicode": "e60a",
      "unicode_decimal": 58890
    },
    {
      "icon_id": "1629916",
      "name": "爱心",
      "font_class": "icon-test",
      "unicode": "e62a",
      "unicode_decimal": 58922
    },
    {
      "icon_id": "2418266",
      "name": "下载",
      "font_class": "xiazai",
      "unicode": "e674",
      "unicode_decimal": 58996
    },
    {
      "icon_id": "4328008",
      "name": "播放",
      "font_class": "bofang1",
      "unicode": "e645",
      "unicode_decimal": 58949
    },
    {
      "icon_id": "4485681",
      "name": "转发",
      "font_class": "zhuanfa",
      "unicode": "e601",
      "unicode_decimal": 58881
    },
    {
      "icon_id": "5328296",
      "name": "57-向上箭头",
      "font_class": "-xiangshangjiantou",
      "unicode": "e733",
      "unicode_decimal": 59187
    },
    {
      "icon_id": "6548572",
      "name": "添加",
      "font_class": "tianjia",
      "unicode": "e65e",
      "unicode_decimal": 58974
    },
    {
      "icon_id": "8288959",
      "name": "爱心",
      "font_class": "aixin",
      "unicode": "e85c",
      "unicode_decimal": 59484
    },
    {
      "icon_id": "12732494",
      "name": "批量编辑",
      "font_class": "piliangbianji",
      "unicode": "e617",
      "unicode_decimal": 58903
    },
    {
      "icon_id": "13969827",
      "name": "笑脸",
      "font_class": "xiaolian",
      "unicode": "e61b",
      "unicode_decimal": 58907
    },
    {
      "icon_id": "15487181",
      "name": "点赞",
      "font_class": "dianzan",
      "unicode": "e67c",
      "unicode_decimal": 59004
    },
    {
      "icon_id": "18923887",
      "name": "点赞",
      "font_class": "70BasicIcons-all-10",
      "unicode": "e626",
      "unicode_decimal": 58918
    },
    {
      "icon_id": "18924627",
      "name": "下载",
      "font_class": "70BasicIcons-all-40",
      "unicode": "e641",
      "unicode_decimal": 58945
    },
    {
      "icon_id": "18926214",
      "name": "播放",
      "font_class": "70BasicIcons-all-64",
      "unicode": "e659",
      "unicode_decimal": 58969
    }
  ]
}
